MANIFEST.in
README.md
setup.cfg
setup.py
mcworldmanager/__init__.py
mcworldmanager/__main__.py
mcworldmanager/cli.py
mcworldmanager/defaults-config.yml
mcworldmanager/log.py
mcworldmanager.egg-info/PKG-INFO
mcworldmanager.egg-info/SOURCES.txt
mcworldmanager.egg-info/dependency_links.txt
mcworldmanager.egg-info/entry_points.txt
mcworldmanager.egg-info/not-zip-safe
mcworldmanager.egg-info/requires.txt
mcworldmanager.egg-info/top_level.txt
mcworldmanager/core/__init__.py
mcworldmanager/core/analysers.py
mcworldmanager/core/manager.py
mcworldmanager/core/models.py
mcworldmanager/core/util.py
mcworldmanager/report/__init__.py
mcworldmanager/report/region_reporter.py
mcworldmanager/report/report_manager.py
mcworldmanager/report/report_utils.py